hrosailing/__init__.py
hrosailing/_version.py
hrosailing/core/__init__.py
hrosailing/core/computing.py
hrosailing/core/constants.py
hrosailing/core/data.py
hrosailing/core/exceptions.py
hrosailing/core/statistics.py
hrosailing/core/modelfunctions/__init__.py
hrosailing/core/modelfunctions/_models2d.py
hrosailing/cruising/__init__.py
hrosailing/cruising/basics.py
hrosailing/models/__init__.py
hrosailing/models/globe_model.py
hrosailing/models/influencemodel.py
hrosailing/models/weather_model.py
hrosailing/pipeline/__init__.py
hrosailing/pipeline/expander.py
hrosailing/pipeline/extensions.py
hrosailing/pipeline/pipeline.py
hrosailing/pipeline/quality_assurance.py
hrosailing/plotting/__init__.py
hrosailing/plotting/projections.py
hrosailing/polardiagram/__init__.py
hrosailing/polardiagram/_basepolardiagram.py
hrosailing/polardiagram/_polardiagramcurve.py
hrosailing/polardiagram/_polardiagrammultisails.py
hrosailing/polardiagram/_polardiagrampointcloud.py
hrosailing/polardiagram/_polardiagramtable.py
hrosailing/polardiagram/_reading.py
hrosailing/processing/__init__.py
hrosailing/processing/datahandler.py
hrosailing/processing/filter.py
hrosailing/processing/imputator.py
hrosailing/processing/injector.py
hrosailing/processing/interpolator.py
hrosailing/processing/neighbourhood.py
hrosailing/processing/regressor.py
hrosailing/processing/sampler.py
hrosailing/processing/smoother.py
hrosailing/processing/weigher.py
hrosailing-0.12.0.dist-info/LICENSE
hrosailing-0.12.0.dist-info/METADATA
hrosailing-0.12.0.dist-info/WHEEL
hrosailing-0.12.0.dist-info/top_level.txt
hrosailing-0.12.0.dist-info/RECORD
