Metadata-Version: 2.1
Name: hrosailing
Version: 0.12.0
Summary: Python library for Polar (Performance) Diagrams
Home-page: https://github.com/hrosailing/hrosailing
Author: Valentin Dannenberg & Robert Schueler
Author-email: valentin.dannenberg2@uni-rostock.de
Project-URL: Bug Tracker, https://github.com/hrosailing/hrosailing/issues
Classifier: Programming Language :: Python :: 3.7
Classifier: Programming Language :: Python :: 3.8
Classifier: Programming Language :: Python :: 3.9
Classifier: License :: OSI Approved :: Apache Software License
Classifier: Operating System :: OS Independent
Requires-Python: >=3.7
License-File: LICENSE
